{
  "backend": "ibm_torino",
  "job_id": "d3k9giodd19c738g12og",
  "M": 32,
  "K": 5,
  "sym": 10,
  "shots": 128,
  "ideal_bin": 10,
  "counts": {
    "01010": 95,
    "01100": 1,
    "01110": 3,
    "11110": 1,
    "10011": 2,
    "11001": 1,
    "11011": 1,
    "11111": 1,
    "00010": 5,
    "11100": 2,
    "11010": 4,
    "01011": 5,
    "10000": 2,
    "11000": 1,
    "10010": 1,
    "01000": 1,
    "01001": 1,
    "10001": 1
  },
  "argmax_bits": "01010",
  "argmax_bin": 10,
  "argmax_freq": 0.742188,
  "ok_pm1": true,
  "p_pm1": 0.789062,
  "p_ideal": 0.742188,
  "tvd_delta": 0.257812
}