{
  "K": 8,
  "M": 256,
  "argmax_bin": 145,
  "argmax_bits": "110010001",
  "backend": "ibm_torino",
  "experiment": "qpsk_index",
  "job_id": "d3ksg203qtks738borl0",
  "lift": 0.0,
  "mode": "job_mode_primitive",
  "p_ideal": 0.0,
  "p_pm1": 0.0,
  "shots": 512,
  "sym": 145,
  "timestamp": "2025-10-10T22:59:24",
  "top_counts": {
    "000000000": 5,
    "001110000": 4,
    "010000000": 10,
    "010010000": 10,
    "010010001": 25,
    "100010000": 5,
    "100010001": 21,
    "101010001": 20,
    "101110001": 16,
    "110000001": 17,
    "110001001": 6,
    "110001101": 6,
    "110010000": 11,
    "110010001": 126,
    "110010011": 7,
    "110010101": 7,
    "110100000": 4,
    "110100001": 6,
    "110110001": 5,
    "111010001": 10
  },
  "tvd_delta": 1.0
}